flexaugment/__init__.py
flexaugment/augmentation.py
flexaugment/augmentation_dataset.py
flexaugment/augmentation_scheduler.py
flexaugment/augmenter.py
flexaugment/transforms.py
flexaugment/utils.py
flexaugment-0.0.0.0.2.dist-info/LICENSE
flexaugment-0.0.0.0.2.dist-info/METADATA
flexaugment-0.0.0.0.2.dist-info/WHEEL
flexaugment-0.0.0.0.2.dist-info/top_level.txt
flexaugment-0.0.0.0.2.dist-info/RECORD
